[
    {
        "Month": "-6",
        "D12": "-0.052203331",
        "E12": "0.038150325",
        "b/m": "0.238784492",
        "tbl": "-0.074349053",
        "AAA": "-0.115890309",
        "BAA": "-0.227365047",
        "lty": "0.126725629",
        "ntis": "-0.256445736",
        "Rfree": "-0.044166785",
        "infl": "-0.167277396",
        "ltr": "0.004578254",
        "corpr": "-0.112706013",
        "svar": "-0.02626824",
        "SPvw": "-0.0750091",
        "Aluminum": "0.051906746"
    },
    {
        "Month": "-5",
        "D12": "0.182453021",
        "E12": "0.282224596",
        "b/m": "0.181652442",
        "tbl": "0.203434631",
        "AAA": "-0.291661382",
        "BAA": "0.181791693",
        "lty": "-0.086789712",
        "ntis": "0.15529348",
        "Rfree": "0.147415891",
        "infl": "-0.169218108",
        "ltr": "-0.091560006",
        "corpr": "-0.089662112",
        "svar": "0.04143142",
        "SPvw": "-0.185665891",
        "Aluminum": "-0.017698526"
    },
    {
        "Month": "-4",
        "D12": "-0.103235297",
        "E12": "-0.140961066",
        "b/m": "0.068419151",
        "tbl": "0.033967953",
        "AAA": "0.154159918",
        "BAA": "-0.206849247",
        "lty": "0.127229035",
        "ntis": "-0.07761436",
        "Rfree": "0.057373069",
        "infl": "0.068430178",
        "ltr": "-0.129449755",
        "corpr": "-0.084806696",
        "svar": "-0.010796966",
        "SPvw": "0.132615089",
        "Aluminum": "-0.079409957"
    },
    {
        "Month": "-3",
        "D12": "-0.13897109",
        "E12": "-0.074027762",
        "b/m": "-0.235679761",
        "tbl": "-0.120109491",
        "AAA": "0.000672751",
        "BAA": "-0.128714994",
        "lty": "0.189581543",
        "ntis": "0.111475766",
        "Rfree": "-0.110393018",
        "infl": "0.180694878",
        "ltr": "-0.165190116",
        "corpr": "0.192416117",
        "svar": "-0.205287725",
        "SPvw": "-0.124730811",
        "Aluminum": "0.259840667"
    },
    {
        "Month": "-2",
        "D12": "0.101477414",
        "E12": "-0.027301816",
        "b/m": "0.24206619",
        "tbl": "0.032585379",
        "AAA": "0.000803015",
        "BAA": "0.201959342",
        "lty": "-0.281723529",
        "ntis": "-0.010997439",
        "Rfree": "-0.049650736",
        "infl": "-0.215091884",
        "ltr": "0.034433439",
        "corpr": "0.062590398",
        "svar": "-0.063349955",
        "SPvw": "-0.020014239",
        "Aluminum": "0.160389245"
    },
    {
        "Month": "-1",
        "D12": "-0.1328872",
        "E12": "0.304444939",
        "b/m": "-0.214032292",
        "tbl": "-0.031760033",
        "AAA": "0.144042611",
        "BAA": "0.057759784",
        "lty": "0.091697119",
        "ntis": "-0.073659621",
        "Rfree": "0.083119787",
        "infl": "-0.033831231",
        "ltr": "-0.129590347",
        "corpr": "0.00791622",
        "svar": "-0.14942047",
        "SPvw": "-0.188173816",
        "Aluminum": "0.094054632"
    }
]